vllmocr/__init__.py
vllmocr/config.py
vllmocr/image_processing.py
vllmocr/llm_interface.py
vllmocr/main.py
vllmocr/prompts.py
vllmocr/utils.py
vllmocr/providers/__init__.py
vllmocr/providers/anthropic.py
vllmocr/providers/base.py
vllmocr/providers/google.py
vllmocr/providers/ollama.py
vllmocr/providers/openai.py
vllmocr/providers/openrouter.py
vllmocr-1.0.0.dist-info/METADATA
vllmocr-1.0.0.dist-info/WHEEL
vllmocr-1.0.0.dist-info/entry_points.txt
vllmocr-1.0.0.dist-info/top_level.txt
vllmocr-1.0.0.dist-info/RECORD
