Metadata-Version: 2.4
Name: vllmocr
Version: 1.0.0
Summary: OCR using LLMs
Keywords: ocr,llm,image processing,vllm
Classifier: Development Status :: 3 - Alpha
Classifier: Intended Audience :: Developers
Classifier: License :: OSI Approved :: MIT License
Classifier: Programming Language :: Python :: 3.10
Classifier: Programming Language :: Python :: 3.11
Classifier: Programming Language :: Python :: 3.12
Requires-Python: >=3.10
Requires-Dist: anthropic>=0.39.0
Requires-Dist: openai>=1.50.0
Requires-Dist: google-genai>=0.5.0
Requires-Dist: ollama>=0.3.0
Requires-Dist: requests>=2.31.0
Requires-Dist: PyMuPDF>=1.24.0
Requires-Dist: opencv-python-headless>=4.9.0
Requires-Dist: python-dotenv>=1.0.0
Requires-Dist: typing-extensions>=4.9.0
Provides-Extra: dev
Requires-Dist: pytest>=8.3.5; extra == "dev"
Requires-Dist: pytest-mock>=3.14.0; extra == "dev"
Requires-Dist: datasets>=2.18.0; extra == "dev"
